paradeigma/__init__.py
paradeigma-0.0.1.dist-info/LICENSE
paradeigma-0.0.1.dist-info/METADATA
paradeigma-0.0.1.dist-info/WHEEL
paradeigma-0.0.1.dist-info/top_level.txt
paradeigma-0.0.1.dist-info/RECORD
